mysquishy/__init__.py
mysquishy/_squish.py
mysquishy-0.2.0.dist-info/LICENSE.txt
mysquishy-0.2.0.dist-info/METADATA
mysquishy-0.2.0.dist-info/WHEEL
mysquishy-0.2.0.dist-info/entry_points.txt
mysquishy-0.2.0.dist-info/top_level.txt
mysquishy-0.2.0.dist-info/RECORD
